shopcloud_secrethub/__init__.py
shopcloud_secrethub/__main__.py
shopcloud_secrethub/app.py
shopcloud_secrethub/cli.py
shopcloud_secrethub/exceptions.py
shopcloud_secrethub/test_cli.py
shopcloud_secrethub-2.17.0.data/scripts/secrethub
shopcloud_secrethub-2.17.0.dist-info/LICENSE.txt
shopcloud_secrethub-2.17.0.dist-info/METADATA
shopcloud_secrethub-2.17.0.dist-info/WHEEL
shopcloud_secrethub-2.17.0.dist-info/top_level.txt
shopcloud_secrethub-2.17.0.dist-info/RECORD
