Metadata-Version: 2.1
Name: shopcloud-secrethub
Version: 2.17.0
Summary: CLI tool for the Shopcloud SecretHub
Home-page: https://github.com/Talk-Point/shopcloud-secrethub-cli
Author: Konstantin Stoldt
Author-email: konstantin.stoldt@talk-point.de
License: MIT
Keywords: CLI
License-File: LICENSE.txt
Requires-Dist: requests
